autoppia/__init__.py
autoppia/automata_client/__init__.py
autoppia/automata_client/automata_client.py
autoppia/src/__init__.py
autoppia/src/apps/__init__.py
autoppia/src/apps/adapter.py
autoppia/src/apps/app_api.py
autoppia/src/apps/app_user_conf_service.py
autoppia/src/apps/base_app.py
autoppia/src/apps/factory.py
autoppia/src/apps/interface.py
autoppia/src/apps/router.py
autoppia/src/apps/implementations/__init__.py
autoppia/src/apps/implementations/chatbot.py
autoppia/src/deployment/__init__.py
autoppia/src/integrations/__init__.py
autoppia/src/integrations/adapter.py
autoppia/src/integrations/config.py
autoppia/src/integrations/interface.py
autoppia/src/integrations/implementations/__init__.py
autoppia/src/integrations/implementations/base.py
autoppia/src/integrations/implementations/api/__init__.py
autoppia/src/integrations/implementations/api/api_integration.py
autoppia/src/integrations/implementations/api/interface.py
autoppia/src/integrations/implementations/database/__init__.py
autoppia/src/integrations/implementations/database/interface.py
autoppia/src/integrations/implementations/database/postgres_integration.py
autoppia/src/integrations/implementations/email/__init__.py
autoppia/src/integrations/implementations/email/interface.py
autoppia/src/integrations/implementations/email/smtp_integration.py
autoppia/src/integrations/implementations/web_search/__init__.py
autoppia/src/integrations/implementations/web_search/google_integration.py
autoppia/src/integrations/implementations/web_search/interface.py
autoppia/src/llms/__init__.py
autoppia/src/llms/adapter.py
autoppia/src/llms/interface.py
autoppia/src/llms/providers.py
autoppia/src/llms/registry.py
autoppia/src/llms/implementations/__init__.py
autoppia/src/llms/implementations/anthropic_service.py
autoppia/src/llms/implementations/openai_service.py
autoppia/src/mcp/__init__.py
autoppia/src/mcp/example.py
autoppia/src/mcp/server.py
autoppia/src/mcp/resources/__init__.py
autoppia/src/mcp/tools/__init__.py
autoppia-0.1.0.dist-info/licenses/LICENSE
autoppia-0.1.0.dist-info/METADATA
autoppia-0.1.0.dist-info/WHEEL
autoppia-0.1.0.dist-info/top_level.txt
autoppia-0.1.0.dist-info/RECORD
