Metadata-Version: 2.4
Name: autoppia
Version: 0.1.0
Summary: SDK and tools for interacting with the Autoppia platform and Automata agents.
Home-page: https://autoppia.com
Author: Autoppia Team
Author-email: team@autoppia.com
License: MIT
Classifier: Programming Language :: Python :: 3
Classifier: License :: OSI Approved :: MIT License
Classifier: Operating System :: OS Independent
Requires-Python: >=3.8
License-File: LICENSE
Requires-Dist: python-dotenv
Requires-Dist: openai
Requires-Dist: tiktoken
Requires-Dist: bs4
Requires-Dist: google-api-python-client
Requires-Dist: google-auth-oauthlib
Requires-Dist: python-dateutil
Requires-Dist: selenium
Requires-Dist: injector
Requires-Dist: dependency-injector
Requires-Dist: pymongo
Requires-Dist: asyncio
Requires-Dist: pytest
Requires-Dist: psycopg2-binary
Requires-Dist: langchain
Requires-Dist: langchain-community
Requires-Dist: langchain-openai
Requires-Dist: websockets
Requires-Dist: flask
Requires-Dist: flask-socketio
Requires-Dist: eventlet
Requires-Dist: gevent
Requires-Dist: gevent-websocket
Requires-Dist: sseclient
Dynamic: author
Dynamic: author-email
Dynamic: classifier
Dynamic: description
Dynamic: description-content-type
Dynamic: home-page
Dynamic: license
Dynamic: license-file
Dynamic: requires-dist
Dynamic: requires-python
Dynamic: summary
